{
    "key": "group_65c21153b7fda",
    "title": "Block - Search Form",
    "fields": [
        {
            "key": "field_65c21153c31be",
            "label": "Placeholder",
            "name": "search_form_placeholder",
            "aria-label": "",
            "type": "text",
            "instructions": "",
            "required": 0,
            "conditional_logic": 0,
            "wrapper": {
                "width": "",
                "class": "",
                "id": ""
            },
            "wpml_cf_preferences": 2,
            "default_value": "",
            "maxlength": "",
            "placeholder": "",
            "prepend": "",
            "append": ""
        }
    ],
    "location": [
        [
            {
                "param": "block",
                "operator": "==",
                "value": "wicket\/search-form"
            }
        ]
    ],
    "menu_order": 0,
    "position": "normal",
    "style": "default",
    "label_placement": "top",
    "instruction_placement": "label",
    "hide_on_screen": "",
    "active": true,
    "description": "",
    "show_in_rest": 0,
    "acfml_field_group_mode": "translation",
    "modified": 1707217316
}
